robinpy-0.12.24.data/purelib/dolphin/__init__.py
robinpy-0.12.24.data/purelib/dolphin/excel.cp38-win_amd64.pyd
robinpy-0.12.24.dist-info/METADATA
robinpy-0.12.24.dist-info/WHEEL
robinpy-0.12.24.dist-info/top_level.txt
robinpy-0.12.24.dist-info/RECORD
