Metadata-Version: 2.1
Name: robinpy
Version: 0.12.24
Summary: A beautiful song
Home-page: UNKNOWN
Author: xinebf
Author-email: me@xienbf.com
License: UNKNOWN
Platform: UNKNOWN
Classifier: Programming Language :: Python :: 3
Classifier: License :: OSI Approved :: GNU General Public License v3 (GPLv3)
Classifier: Operating System :: Microsoft :: Windows
Requires-Python: >=3.8, <3.9
Requires-Dist: pywin32
